playstoreapi/__init__.py
playstoreapi/config.py
playstoreapi/device.properties
playstoreapi/googleplay.py
playstoreapi/googleplay_pb2.py
playstoreapi/utils.py
playstoreapi-0.5.8.dist-info/LICENSE.md
playstoreapi-0.5.8.dist-info/METADATA
playstoreapi-0.5.8.dist-info/WHEEL
playstoreapi-0.5.8.dist-info/top_level.txt
playstoreapi-0.5.8.dist-info/RECORD
