Metadata-Version: 2.1
Name: playstoreapi
Version: 0.5.8
Summary: Unofficial python api for google play
Home-page: https://gitlab.com/marzzzello/playstoreapi
Author: NoMore201, marzzzello
Author-email: playstoreapi@07f.de
License: GPL3
Platform: UNKNOWN
License-File: LICENSE.md
Requires-Dist: cryptography (>=2.2)
Requires-Dist: protoc-wheel-0
Requires-Dist: protobuf (>=3.5.2)
Requires-Dist: requests
